pyruster/__init__.py
pyruster/__init__.pyi
pyruster/py.typed
pyruster/rust_option.py
pyruster/rust_result.py
pyruster-0.1.12.dist-info/LICENSE
pyruster-0.1.12.dist-info/METADATA
pyruster-0.1.12.dist-info/WHEEL
pyruster-0.1.12.dist-info/top_level.txt
pyruster-0.1.12.dist-info/RECORD
