Metadata-Version: 2.1
Name: pyruster
Version: 0.1.12
Summary: Implementing some syntax like rust.
Home-page: UNKNOWN
Author: Elling
License: MIT
Platform: UNKNOWN
Requires-Python: >=3.6
License-File: LICENSE
